{"data": {"doi": "10.1109/tvcg.2020.3030373", "title": "Multi-Perspective, Simultaneous Embedding", "year": "2020", "conferenceName": "InfoVis", "authors": "Md. Iqbal Hossain;Vahan Huroyan;Stephen G. Kobourov;Raymundo Navarrete", "citationCount": "0", "affiliation": "Hossain, MI (Corresponding Author), Univ Arizona, Dept Comp Sci, Tucson, AZ 85721 USA. Hossain, Md Iqbal; Kobourov, Stephen, Univ Arizona, Dept Comp Sci, Tucson, AZ 85721 USA. Huroyan, Vahan; Navarrete, Raymundo, Univ Arizona, Dept Math, Tucson, AZ 85721 USA.", "countries": "USA", "abstract": "We describe MPSE: a Multi-Perspective Simultaneous Embedding method for visualizing high-dimensional data, based on multiple pairwise distances between the data points. Specifically, MPSE computes positions for the points in 3D and provides different views into the data by means of 2D projections (planes) that preserve each of the given distance matrices. We consider two versions of the problem: fixed projections and variable projections. MPSE with fixed projections takes as input a set of pairwise distance matrices defined on the data points, along with the same number of projections and embeds the points in 3D so that the pairwise distances are preserved in the given projections. MPSE with variable projections takes as input a set of pairwise distance matrices and embeds the points in 3D while also computing the appropriate projections that preserve the pairwise distances. The proposed approach can be useful in multiple scenarios: from creating simultaneous embedding of multiple graphs on the same set of vertices, to reconstructing a 3D object from multiple 2D snapshots, to analyzing data from multiple points of view. We provide a functional prototype of MPSE that is based on an adaptive and stochastic generalization of multi-dimensional scaling to multiple distances and multiple variable projections. We provide an extensive quantitative evaluation with datasets of different sizes and using different number of projections, as well as several examples that illustrate the quality of the resulting solutions.", "keywords": "Graph visualization,Dimensionality reduction,Multidimensional scaling,Mental map preservation", "link": "http://dx.doi.org/10.1109/TVCG.2020.3030373", "refList": ["10.1016/j.cag.2014.01.006", "10.1109/tvcg.2007.70443", "10.1007/978-3-642-04843-2\\_36", "10.1111/cgf.12639", "10.1109/tvcg.2019.2944182", "10.1109/tvcg.2019.2934811", "10.1007/978-1-4757-2261-1", "10.1145/3173574.3174209", "10.1016/j.neucom.2006.11.018", "10.1109/tpami.2013.57", "10.2307/2334381", "10.1109/tpami.2012.88", "10.1109/tvcg.2017.2661309", "10.1080/13506280444000102.http://www.uvt.nl/ticc", "10.1111/j.1467-8659.2010.01835.x", "10.1109/vl.1996.545307", "10.1109/iv.2009.25", "10.1109/msp.2010.939739", "10.1063/1.3067728", "10.2312/pe/eurovast/eurovast10/013-018", "10.1109/vast.2010.5652460", "10.25365/thesis.51534", "10.21105/joss.00861", "10.1145/1007730.1007731", "10.1109/tvcg.2013.20", "10.1109/tvcg.2011.220", "10.1037/h0071325", "10.1109/vast.2012.6400488", "10.1109/tvcg.2007.70535", "10.1198/jasa.2009.0111", "10.1109/tvcg.2016.2598495", "10.1109/tvcg.2017.2698041", "10.1109/tvcg.2015.2467717", "10.1111/j", "10.1016/j.neucom.2014.07.071", "10.1126/science.290.5500.2323", "10.1109/tvcg.2013.153", "10.2312/pe/eurovast", "10.1109/tvcg.2018.2846735", "10.1007/bf02289530", "10.1111/j.1745-3984.2003.tb01108.x", "10.1177/1473871615600010", "10.5555/3053814.3053816", "10.1109/tvcg.2018.2865194"], "wos": 1, "children": [], "len": 1}, "index": 1026, "embedding": [0.26427456736564636, -0.24374806880950928, -0.6070677042007446, -1.9401246309280396, -0.5598564147949219, 0.16650904715061188, -0.7643030881881714, -0.4584938585758209, 0.3387182950973511, -0.7373658418655396, 0.8940240740776062, -1.1077367067337036, -0.15792734920978546, -0.7472437024116516, 0.9410538077354431, -0.35318270325660706, 0.22150668501853943, 0.06589167565107346, 0.43863141536712646, -0.3914463520050049, -0.06630208343267441, -0.6124352812767029, -0.24719014763832092, -0.15392345190048218, -2.343374252319336, 0.05785536766052246, -0.17719954252243042, 0.17115968465805054, -0.5880303382873535, 1.6198651790618896, 0.1135394498705864, -0.07587476819753647], "projection": [2.646294355392456, 2.5291686058044434], "size": 1, "height": 1, "width": 1}