{"data": {"doi": "10.1111/cgf.13183", "year": "2017", "title": "Visual Analysis of Confocal Raman Spectroscopy Data using Cascaded Transfer Function Design", "conferenceName": "EuroVis", "authors": "Christoph M. Schikora;Markus Plack;Rainer Bornemann;Peter Haring Bol{\\'{\\i}}var;Andreas Kolb", "citationCount": "0", "affiliation": "Schikora, CM (Corresponding Author), Univ Siegen, Comp Graph \\& Multimedia Syst, Siegen, Germany.\nSchikora, Christoph M.; Plack, Markus; Kolb, Andreas, Univ Siegen, Comp Graph \\& Multimedia Syst, Siegen, Germany.\nBornemann, Rainer; Bolivar, Peter Haring, Univ Siegen, High Frequency \\& Quantum Elect, Siegen, Germany.", "countries": "Germany", "abstract": "2D Confocal Raman Microscopy (CRM) data consist of high dimensional per-pixel spectral data of 1000 bands and allows for complex spectral and spatial-spectral analysis tasks, i.e., in material discrimination, material thickness, and spatial material distributions. Currently, simple integral methods are commonly applied as visual analysis solutions to CRM data which exhibit restricted discrimination power in various regards. In this paper we present a novel approach for the visual analysis of 2D multispectral CRM data using multi-variate visualization techniques. Due to the large amount of data and the demand of an explorative approach without a-priori restriction, our system allows for arbitrary interactive (de)selection of varaibles w/o limitation and an unrestricted online definition/construction of new, combined properties. Our approach integrates CRM specific quantitative measures and handles material-related features for mixed materials in a quantitative manner. Technically, we realize the online definition/construction of new, combined properties as semi-automatic, cascaded, 1D and 2D multidimensional transfer functions (MD-TFs). By interactively incorporating new (raw or derived) properties, the dimensionality of the MD-TF space grows during the exploration procedure and is virtually unlimited. The final visualization is achieved by an enhanced color mixing step which improves saturation and contrast.", "keywords": "", "link": "https://doi.org/10.1111/cgf.13183", "refList": ["10.1016/j.sab.2006.12.002", "10.1021/nl061702a", "10.1007/978-3-642-12522-5\\_4", "10.1016/j.carbon.2016.01.001", "10.1137/040616024", "10.1016/j.cag.2012.02.007", "10.1111/cgf.12365", "10.2312/vissym/eur0vis05/117-123", "10.1007/s11664-009-0803-6", "10.1109/mcse.2012.27", "10.1109/tvcg.2002.1021579", "10.1007/978-3-540-85567-5\\_50", "10.1109/pacificvis.2010.5429612", "10.1109/tgrs.2010.2051553", "10.1109/tvcg.2007.70591", "10.1021/ac034173t", "10.1366/000370210792434350", "10.1111/cgf.12934", "10.1109/tvcg.2012.110", "10.1109/tvcg.2012.105", "10.1109/tvcg.2006.164", "10.1109/tvcg.2009.199", "10.1109/visual.2003.1250412", "10.1109/igarss.2011.6049397", "10.1007/978-3-642-12522-5", "10.1109/pacificvis.2013.6596129", "10.1039/c4an01061b", "10.1109/tvcg.2011.261"], "wos": 1, "children": [], "len": 1}, "index": 1401, "embedding": [-1.8881237506866455, -0.26742973923683167, -1.0271400213241577, -0.31003087759017944, -0.1910475641489029, 0.16650904715061188, 4.877262115478516, 1.4302507638931274, 6.557957649230957, -0.6888176798820496, 2.1838364601135254, -0.9658841490745544, 0.08829163014888763, 1.8871333599090576, -0.6648035645484924, -0.5062769055366516, -0.03365722671151161, 0.0788058489561081, -0.22435054183006287, -0.0667189285159111, -0.06630208343267441, 0.33132481575012207, -0.2185245305299759, -0.114951491355896, -1.2825369834899902, 1.9319838285446167, -0.5328229665756226, -0.17058739066123962, -0.544016420841217, -2.594913959503174, 0.18127281963825226, -0.8552394509315491], "projection": [-1.1090526580810547, -19.283597946166992], "size": 1, "height": 1, "width": 1}