{"data": {"doi": "10.1111/cgf.13986", "year": "2020", "title": "Metro Maps on Octilinear Grid Graphs", "conferenceName": "EuroVis", "authors": "Hannah Bast;Patrick Brosi;Sabine Storandt", "citationCount": "0", "affiliation": "Bast, H (Corresponding Author), Univ Freiburg, Dept Comp Sci, Freiburg, Germany.\nBast, Hannah; Brosi, Patrick, Univ Freiburg, Dept Comp Sci, Freiburg, Germany.\nStorandt, Sabine, Univ Konstanz, Dept Comp \\& Informat Sci, Constance, Germany.", "countries": "Germany", "abstract": "Schematic transit maps (often called ``metro maps{''} in the literature) are important to produce comprehensible visualizations of complex public transit networks. In this work, we investigate the problem of automatically drawing such maps on an octilinear grid with an arbitrary (but optimal) number of edge bends. Our approach can naturally deal with obstacles that should be respected in the final drawing (points of interest, rivers, coastlines) and can prefer grid edges near the real-world course of a line. This allows our drawings to be combined with existing maps, for example as overlays in map services. We formulate an integer linear program which can be used to solve the problem exactly. We also provide a fast approximation algorithm which greedily calculates shortest paths between node candidates on the underlying octilinear grid graph. Previous work used local search techniques to update node positions until a local optimum was found, but without guaranteeing octilinearity. We can thus calculate nearly optimal metro maps in a fraction of a second even for complex networks, enabling the interactive use of our method in map editors.", "keywords": "", "link": "https://doi.org/10.1111/cgf.13986", "refList": ["10.1109/tvcg.2010.81", "10.1109/iv.2004.1320168", "10.1109/iv.2004.1320189", "10.1109/tvcg.2015.2430290", "10.1109/tvcg.2011.205", "10.1109/percomw.2019.8730757", "10.1109/iv.2005.26", "10.1145/3274895.3274959", "10.1145/3337790", "10.1111/cgf.12113", "10.1109/bigcomp.2014.6741398", "10.1016/j.jvlc.2005.09.001", "10.1111/j.1467-8659.2012.03085.x", "10.1007/978-3-662-45803-7\\_28"], "wos": 1, "children": [{"doi": "10.1109/tvcg.2020.3030344", "title": "Deep Volumetric Ambient Occlusion", "year": "2020", "conferenceName": "SciVis", "authors": "Dominik Engel;Timo Ropinski", "citationCount": "0", "affiliation": "Engel, D (Corresponding Author), Ulm Univ, Ulm, Germany. Engel, Dominik; Ropinski, Timo, Ulm Univ, Ulm, Germany. Ropinski, Timo, Linkoping Univ, Norrkoping, Sweden.", "countries": "Sweden;Germany", "abstract": "We present a novel deep learning based technique for volumetric ambient occlusion in the context of direct volume rendering. Our proposed Deep Volumetric Ambient Occlusion (DVAO) approach can predict per-voxel ambient occlusion in volumetric data sets, while considering global information provided through the transfer function. The proposed neural network only needs to be executed upon change of this global information, and thus supports real-time volume interaction. Accordingly, we demonstrate DVAO's ability to predict volumetric ambient occlusion, such that it can be applied interactively within direct volume rendering. To achieve the best possible results, we propose and analyze a variety of transfer function representations and injection strategies for deep neural networks. Based on the obtained results we also give recommendations applicable in similar volume learning scenarios. Lastly, we show that DVAO generalizes to a variety of modalities, despite being trained on computed tomography data only.", "keywords": "Volume illumination,deep learning,direct volume rendering", "link": "http://dx.doi.org/10.1109/TVCG.2020.3030344", "refList": ["10.1287/opre.21.2.498", "10.1111/cgf.12722", "10.1145/2187836.2187957", "10.1109/tvcg.2015.2430290", "10.1109/tvcg.2013.76", "10.1177/1473871618754343", "10.2307/2412323", "10.3390/ijms19092477", "10.1109/tvcg.2014.2346249", "10.1111/j.1467-8659.2009.01452.x", "10.1109/iv.2005.26", "10.1145/3274895.3274959", "10.1007/978-3-319-08404-6\\_23", "10.7155/jgaa.00364", "10.1007/978-1-4612-4380-9\\_6", "10.1109/tvcg.2014.2346312", "10.1109/mcg.2010.101", "10.1016/j.jda.2011.12.009", "10.1111/cgf.12880", "10.1007/3-540-58950-3", "10.1111/j.1467-8659.2012.03080.x", "10.1111/cgf.13986", "10.1109/tvcg.2012.252", "10.1109/tvcg.2014.2346422", "10.1109/vl.1996.545307", "10.1109/tvcg.2012.212", "10.1371/journal.pone.0116902", "10.1559/152304075784313304", "10.1111/cgf.12656", "10.1109/tvcg.2011.205", "10.1109/tvcg.2010.210", "10.1109/tvcg.2011.56", "10.1016/j.jda.2017.08.001", "10.1111/cgf.14030", "10.1109/tvcg.2013.184", "10.1016/0020-0190(89)90102-6", "10.1109/tvcg.2009.122", "10.1371/journal.pone.0211234", "10.1145/3366423.3380152", "10.2307/3001913", "10.1007/s10107-003-0410-x", "10.1145/2810012", "10.1145/371920.372079", "10.1109/tvcg.2014.2346248", "10.1016/j.jvlc.2012.02.001", "10.1109/tvcg.2010.24", "10.1016/j.jvlc.2014.09.002", "10.1002/spe.4380211102", "10.1002/jgt.3190110306", "10.1287/opre.6.6.791", "10.1109/vast.2007.4389013", "10.1007/978-3-540-87730-1\\_6", "10.1109/tvcg.2015.2467992", "10.1109/tvcg.2010.28", "10.1109/tvcg.2013.196", "10.1145/321043.321046", "10.1016/j.ijhcs.2016.06.003", "10.1109/tvcg.2010.81", "10.1109/iv.2004.1320189", "10.1007/s00453-017-0350-0", "10.1016/j.intcom.2007.05.004", "10.1109/tvcg.2011.186", "10.1007/978-3-662-44043-8\\_1", "10.1007/978-3-540-33037-0\\_14", "10.1145/2735624", "10.1145/1842993.1843034"], "wos": 1, "children": [], "len": 1}], "len": 3}, "index": 1576, "embedding": [-0.24973700940608978, -0.1100221499800682, 0.668681263923645, 1.4118975400924683, -0.6274024844169617, 0.16650904715061188, -0.7643030881881714, -0.8897074460983276, -0.4787178039550781, -0.9009531736373901, -0.2555254101753235, -0.5207395553588867, -0.15792734920978546, 0.6662418246269226, -0.3333565592765808, 0.1252666860818863, -0.23965154588222504, 0.06589167565107346, -0.3843677341938019, 1.0738023519515991, -0.06630208343267441, -0.2060512900352478, 0.27456527948379517, -0.15392345190048218, 0.22739097476005554, 0.05785536766052246, -0.5536867380142212, -0.1945725977420807, 0.29144659638404846, -0.4137383997440338, -0.1340135782957077, 0.13717618584632874], "projection": [-3.048933744430542, 6.03362512588501], "size": 2, "height": 2, "width": 1}