{"data": {"doi": "10.1109/tvcg.2019.2934257", "title": "Toward Localized Topological Data Structures: Querying the Forest for the Tree", "year": "2019", "conferenceName": "SciVis", "authors": "Pavol Klacansky;Attila Gyulassy;Peer-Timo Bremer;Valerio Pascucci", "citationCount": "1", "affiliation": "Klacansky, P (Corresponding Author), Univ Utah, Sci Comp \\& Imaging Inst, Salt Lake City, UT 84112 USA. Klacansky, Pavol; Gyulassy, Attila; Pascucci, Valerio, Univ Utah, Sci Comp \\& Imaging Inst, Salt Lake City, UT 84112 USA. Bremer, Peer-Timo, Lawrence Livermore Natl Lab, Livermore, CA USA.", "countries": "USA", "abstract": "Topological approaches to data analysis can answer complex questions about the number, connectivity, and scale of intrinsic features in scalar data. However, the global nature of many topological structures makes their computation challenging at scale, and thus often limits the size of data that can be processed. One key quality to achieving scalability and performance on modern architectures is data locality, i.e., a process operates on data that resides in a nearby memory system, avoiding frequent jumps in data access patterns. From this perspective, topological computations are particularly challenging because the implied data structures represent features that can span the entire data set, often requiring a global traversal phase that limits their scalability. Traditionally, expensive preprocessing is considered an acceptable trade-off as it accelerates all subsequent queries. Most published use cases, however, explore only a fraction of all possible queries, most often those returning small, local features. In these cases, much of the global information is not utilized, yet computing it dominates the overall response time. We address this challenge for merge trees, one of the most commonly used topological structures. In particular, we propose an alternative representation, the merge forest, a collection of local trees corresponding to regions in a domain decomposition. Local trees are connected by a bridge set that allows us to recover any necessary global information at query time. The resulting system couples (i) a preprocessing that scales linearly in practice with (ii) fast runtime queries that provide the same functionality as traditional queries of a global merge tree. We test the scalability of our approach on a shared-memory parallel computer and demonstrate how data structure locality enables the analysis of large data with an order of magnitude performance improvement over the status quo. Furthermore, a merge forest reduces the memory overhead compared to a global merge tree and enables the processing of data sets that are an order of magnitude larger than possible with previous algorithms.", "keywords": "Merge tree,parallel computation,topology", "link": "http://dx.doi.org/10.1109/TVCG.2019.2934257", "refList": ["10.1109/ldav.2017.8231846", "10.1145/276884.276892", "10.1090/mbk/069", "10.1007/s00454-002-2885-2", "10.1109/tvcg.2015.2452919", "10.1016/0956-0521(91)90014-v", "10.1145/262839.269238", "10.1145/364099.364331", "10.1016/j.comgeo.2006.05.009", "10.1109/ldav.2016.7874333", "10.1080/16864360.2017.1419648", "10.1016/s0925-7721(02)00093-7", "10.1145/2517327.2442526", "10.1109/tvcg.2017.2743938", "10.1016/j.proci.2014.05.147", "10.1109/tvcg.2010.253", "10.1103/physrevlett.113.155005", "10.1007/978-3-319-44684-420", "10.1109/ldav.2016.7874312", "10.1007/b106657\\_2", "10.1109/sc.2014.88", "10.1109/ldav.2015.7348066", "10.1007/978-3-319-04099-86", "10.1109/ldav.2012.6378962", "10.1109/pacificvis.2017.8031584", "10.2140/camcos.2016.11.37", "10.1016/j.combustflame.2014.08.021", "10.1109/tvcg.2006.22", "10.1007/pl00009159", "10.1007/s00453-003-1052-3", "10.1109/tvcg.2007.47", "10.1017/jfm.2015.268", "10.1007/s00454-017-9901-z", "10.1145/62.2160", "10.1145/2996913.2996952", "10.1145/1868237.1868249", "10.1145/77635.77639", "10.1016/j.comgeo.2004.05.002", "10.1088/1742-6596/180/1/012086", "10.1109/pacificvis.2015.7156387", "10.1109/tpds.2019.2898436", "10.1145/1463822.1463869", "10.1109/tvcg.2017.2744238", "10.1109/hipc.2012.6507496", "10.1109/tvcg.2006.162", "10.1017/s0022112004009681", "10.2307/2317380"], "wos": 1, "children": [], "len": 1}, "index": 858, "embedding": [-0.7260757088661194, 0.3102011978626251, -0.6976539492607117, -2.3949873447418213, -0.13929793238639832, 0.16650904715061188, -0.7182635068893433, -0.9943554401397705, 0.1709330826997757, -0.8018340468406677, 1.0305274724960327, -0.784088671207428, 0.37279731035232544, -1.0944232940673828, 0.030379993841052055, -0.5253733396530151, 0.10375568270683289, 0.07991757988929749, 0.7437570095062256, -0.575380802154541, -0.06630208343267441, -0.6180840134620667, -0.12160404771566391, -0.13207590579986572, -2.532860279083252, 0.09441477060317993, 0.015979507938027382, 0.5791722536087036, -0.23429563641548157, -0.8897154331207275, 0.2667645812034607, -0.15092690289020538], "projection": [0.5638997554779053, 3.4940567016601562], "size": 1, "height": 1, "width": 1}