{"data": {"doi": "10.1109/tvcg.2019.2934310", "title": "Extraction and Visual Analysis of Potential Vorticity Banners around the Alps", "year": "2019", "conferenceName": "SciVis", "authors": "Robin Bader;Michael Sprenger;Nikolina Ban;Stefan R\u00fcdis\u00fchli;Christoph Sch\u00e4r;Tobias G\u00fcnther", "citationCount": "0", "affiliation": "Bader, R (Corresponding Author), Swiss Fed Inst Technol, Dept Comp Sci, Zurich, Switzerland. Bader, Robin; Guenther, Tobias, Swiss Fed Inst Technol, Dept Comp Sci, Zurich, Switzerland. Sprenger, Michael; Ban, Nikolina; Ruedisuehli, Stefan; Schaer, Christoph, Swiss Fed Inst Technol, Inst Atmospher \\& Climate Sci, Zurich, Switzerland.", "countries": "Switzerland", "abstract": "Potential vorticity is among the most important scalar quantities in atmospheric dynamics. For instance, potential vorticity plays a key role in particularly strong wind peaks in extratropical cyclones and it is able to explain the occurrence of frontal rain bands. Potential vorticity combines the key quantities of atmospheric dynamics, namely rotation and stratification. Under suitable wind conditions elongated banners of potential vorticity appear in the lee of mountains. Their role in atmospheric dynamics has recently raised considerable interest in the meteorological community for instance due to their influence in aviation wind hazards and maritime transport. In order to support meteorologists and climatologists in the analysis of these structures, we developed an extraction algorithm and a visual exploration framework consisting of multiple linked views. For the extraction we apply a predictor-corrector algorithm that follows streamlines and realigns them with extremal lines of potential vorticity. Using the agglomerative hierarchical clustering algorithm, we group banners from different sources based on their proximity. To visually analyze the time-dependent banner geometry, we provide interactive overviews and enable the query for detail on demand, including the analysis of different time steps, potentially correlated scalar quantities, and the wind vector field. In particular, we study the relationship between relative humidity and the banners for their potential in indicating the development of precipitation. Working with our method, the collaborating meteorologists gained a deeper understanding of the three-dimensional processes, which may spur follow-up research in the future.", "keywords": "Scientific Visualization,potential vorticity,meteorology,feature extraction", "link": "http://dx.doi.org/10.1109/TVCG.2019.2934310", "refList": ["10.1002/qj.49710042520", "10.1111/j.1467-8659.2009.01702.x", "10.1111/cgf.13319", "10.1175/1520-0469(1998)055", "10.1007/bf01475602", "10.1143/jpsj.66.1331", "10.1109/tvcg.2013.2297914", "10.1007/978-3-540-88606-8\\_6", "10.1175/1520-0477(2001)082", "10.1175/mwr-d-16-0042.1", "10.1007/s00703-001-0592-9", "10.1002/qj.49710544615", "10.1111/cgf.13163", "10.1007/bf01446807", "10.1109/visual.1994.346327", "10.1109/visual.1999.809896", "10.1109/tvcg.2011.78", "10.1109/tvcg.2015.2467200", "10.2514/2.744", "10.1145/1013208.1013209", "10.1007/978-3", "10.1111/cgf.12933", "10.1175/1520-0477(2002)083", "10.1007/978-94-015-8765-5", "10.1175/2011mwr3504.1", "10.1007/s007030170008", "10.5194/gmd-9-3393-2016", "10.1175/bams-d-15-00299.1", "10.1002/2014gl062588", "10.1256/smsqj.47001", "10.1175/2010mwr3334.1", "10.1109/tvcg.2017.2779501", "10.1256/qj.02.47", "10.1111/cgf.13439", "10.5194/gmd-2017-230", "10.1109/visual.2003.1250376", "10.14529/jsfi140103", "10.1109/tvcg.2017.2743989", "10.1109/tvcg.2007.70545", "10.1111/j.1467-8659.2003.00723.x", "10.1109/tvcg.2007.1053", "10.1002/qj.828", "10.1002/2016jd026013", "10.1007/bf01450097"], "wos": 1, "children": [], "len": 1}, "index": 881, "embedding": [-0.8274128437042236, 0.15021944046020508, -1.0626764297485352, -1.0758053064346313, -0.6737499833106995, 0.16650904715061188, 2.149470567703247, 1.9198341369628906, -0.4176805317401886, 0.24531082808971405, -0.5595630407333374, -0.7247387766838074, -0.13027368485927582, -0.617284893989563, -0.12225726991891861, 0.8730440139770508, -0.1716480255126953, 0.07420150190591812, -0.6413080096244812, 0.5195079445838928, -0.06630208343267441, 1.730859398841858, -1.0862054824829102, 0.06289523094892502, -1.7992737293243408, 0.09751410037279129, -0.5483691096305847, -0.1611158847808838, 0.5749635100364685, 0.4046998620033264, -0.7546910047531128, 0.08951073884963989], "projection": [-3.9571919441223145, -2.101229429244995], "size": 1, "height": 1, "width": 1}