{"data": {"doi": "10.1109/tvcg.2019.2934668", "title": "FlowSense: A Natural Language Interface for Visual Data Exploration within a Dataflow System", "year": "2019", "conferenceName": "VAST", "authors": "Bowen Yu 0004;Cl\u00e1udio T. Silva", "citationCount": "4", "affiliation": "Yu, BW (Corresponding Author), NYU, New York, NY 10003 USA. Yu, Bowen; Silva, Claudio T., NYU, New York, NY 10003 USA.", "countries": "USA", "abstract": "Dataflow visualization systems enable flexible visual data exploration by allowing the user to construct a dataflow diagram that composes query and visualization modules to specify system functionality. However learning dataflow diagram usage presents overhead that often discourages the user. In this work we design FlowSense, a natural language interface for dataflow visualization systems that utilizes state-of-the-art natural language processing techniques to assist dataflow diagram construction. FlowSense employs a semantic parser with special utterance tagging and special utterance placeholders to generalize to different datasets and dataflow diagrams. It explicitly presents recognized dataset and diagram special utterances to the user for dataflow context awareness. With FlowSense the user can expand and adjust dataflow diagrams more conveniently via plain English. We apply FlowSense to the VisFlow subset-flow visualization system to enhance its usability. We evaluate FlowSense by one case study with domain experts on a real-world data analysis problem and a formal user study.", "keywords": "Natural language interface,dataflow visualization system,visual data exploration", "link": "http://dx.doi.org/10.1109/TVCG.2019.2934668", "refList": ["10.1109/38.31462", "10.1145/1292609.1292620", "10.1109/visual.2005.1532788", "10.1109/tvcg.2007.70594", "10.1017/s135132490000005x.http://j0urnals.cambridge.0rg/article\\_", "10.1145/3025171.3025227", "10.1109/vl.1996.545307", "10.1111/cgf.12131", "10.1109/mci.2018.2840738", "10.3115/v1/p14-5010", "10.1109/tvcg.2017.2744684", "10.1109/infvis.2005.1532136", "10.1109/tvcg.2017.2745219", "10.1145/2984511.2984588", "10.1117/12.309533", "10.1093/nar/gkt328", "10.1109/tvcg.2012.323", "10.1017/s135132490000005x", "10.1109/mcg.2009.130", "10.1146/annurev-linguist-030514-125312", "10.1023/a:1011368926479", "10.1145/375360.375365", "10.1111/cgf.12628", "10.1145/2807442.2807478", "10.1109/tvcg.2010.164", "10.1109/tvcg.2016.2598497", "10.1109/tse.1986.6312901", "10.1117/12.342832"], "wos": 1, "children": [{"doi": "10.1111/cgf.14035", "year": "2020", "title": "Survey on the Analysis of User Interactions and Visualization Provenance", "conferenceName": "EuroVis", "authors": "Kai Xu;Alvitta Ottley;Conny Walchshofer;Marc Streit;Remco Chang;John E. Wenskovitch", "citationCount": "0", "affiliation": "Xu, K (Corresponding Author), Middlesex Univ, London, England.\nXu, Kai, Middlesex Univ, London, England.\nOttley, Alvitta, Washington Univ, St Louis, MO 63110 USA.\nWalchshofer, Conny; Streit, Marc, Johannes Kepler Univ Linz, Linz, Austria.\nChang, Remco, Tufts Univ, Medford, MA 02155 USA.\nWenskovitch, John, Virginia Tech, Blacksburg, VA USA.", "countries": "USA;England;Austria", "abstract": "There is fast-growing literature on provenance-related research, covering aspects such as its theoretical framework, use cases, and techniques for capturing, visualizing, and analyzing provenance data. As a result, there is an increasing need to identify and taxonomize the existing scholarship. Such an organization of the research landscape will provide a complete picture of the current state of inquiry and identify knowledge gaps or possible avenues for further investigation. In this STAR, we aim to produce a comprehensive survey of work in the data visualization and visual analytics field that focus on the analysis of user interaction and provenance data. We structure our survey around three primary questions: (1) WHY analyze provenance data, (2) WHAT provenance data to encode and how to encode it, and (3) HOW to analyze provenance data. A concluding discussion provides evidence-based guidelines and highlights concrete opportunities for future development in this emerging area. The survey and papers discussed can be explored online interactively at https://provenance-survey.caleydo.org.", "keywords": "", "link": "https://doi.org/10.1111/cgf.14035", "refList": ["10.1145/3186266", "10.1145/3185524", "10.1109/tvcg.2014.2346575", "10.1109/tvcg.2016.2598471", "10.1109/tvcg.2016.2598446", "10.1145/2856767.2856779", "10.1109/tvcg.2017.2745278", "10.1109/tvcg.2015.2467871", "10.1109/tvcg.2019.2934668", "10.1145/3301275.3302307", "10.1145/2207676.2208293", "10.1111/cgf.13402", "10.1111/cgf.12895", "10.1145/1084805.1084812", "10.1145/2983923", "10.1007/978-1-4419-5874-7\\_12", "10.1109/mcg.2010.18", "10.1109/tvcg.2015.2467153", "10.1109/tvcg.2013.211", "10.1145/3172944.3172964", "10.1145/3290605.3300360", "10.1109/tvcg.2009.199", "10.1109/vast.2016.7883515", "10.1145/2207676.2208412", "10.1145/1979742.1979570", "10.1145/2207676.2208565", "10.1109/tvcg.2017.2745078", "10.1109/tvcg.2013.226", "10.1145/3301275.3302270", "10.1145/2882903.2882919", "10.1109/tvcg.2013.132", "10.1007/978-1-4614-3223-4\\_6", "10.1007/978-1-4899-7993-3\\_80747-1", "10.1145/2449396.2449439", "10.4230/dagrep.8.11.35", "10.1111/cgf.13424", "10.1109/tvcg.2015.2467613", "10.1109/mcse.2007.106", "10.1109/vast.2014.7042486", "10.1145/3126594.3126653", "10.1145/2591510", "10.1109/vast.2017.8585665", "10.1109/tvcg.2017.2744684", "10.1109/vast.2009.5333564", "10.1111/cgf.12631", "10.1145/2702123.2702262", "10.1111/cgf.13717", "10.2312/evs.20191181", "10.1111/cgf.12925", "10.1145/2702123.2702590", "10.1109/tvcg.2015.2467551", "10.1145/3025171.3025187", "10.1145/3316416.3316418", "10.1109/tvcg.2015.2468078", "10.1109/mcg.2014.73", "10.1109/tvcg.2017.2744479", "10.1109/tvcg.2018.2859969", "10.1109/tvcg.2014.2346321", "10.1109/tvcg.2007.70589", "10.1007/s13218-012-0167-6", "10.1111/cgf.13670", "10.1145/2807442.2807478", "10.1111/cgf.13715", "10.1109/tvcg.2012.23", "10.1109/tvcg.2017.2745279", "10.1109/tvcg.2013.164", "10.1109/vast.2008.4677365", "10.1145/3301275.3302291", "10.1109/tvcg.2012.260", "10.1109/tvcg.2010.177", "10.1109/tvcg.2018.2865024", "10.1109/mcg.2015.51", "10.1145/2240236.2240260", "10.1109/tvcg.2016.2599030.2", "10.1109/tvcg.2007.70515", "10.1109/tvcg.2012.175", "10.1109/mcg.2019.2941856", "10.1109/tvcg.2008.137", "10.1016/j.visinf.2018.09.003", "10.4304/jmm.9.5.635-643", "10.1109/tvcg.2017.2744843", "10.1111/cgf.13405", "10.1145/2633043", "10.1109/tvcg.2009.129", "10.1109/tvcg.2019.2934609", "10.1111/cgf.12924", "10.1145/2702123.2702376", "10.1109/vast.2017.8585669", "10.1145/1502650.1502695", "10.1111/cgf.13730", "10.1109/tvcg.2013.124", "10.1109/tvcg.2017.2744805", "10.1109/mcg.2009.49", "10.1109/vast.2015.7347625", "10.1145/3009973", "10.1145/2470654.2470723", "10.1109/vast.2016.7883520", "10.1109/vast.2014.7042492", "10.1145/2984511.2984588", "10.1111/cgf.12391", "10.1561/1900000006", "10.1007/s00778-017-0486-1", "10.1109/vast.2009.5333020", "10.1145/1926385.1926423", "10.1145/1057977.1057978", "10.1145/3290605.3300892", "10.1111/j.1467-8659.2011.01928.x", "10.1109/tvcg.2013.188", "10.1109/tvcg.2015.2467191", "10.1109/iccicct.2014.6993023", "10.1145/3290605.3300874", "10.1145/2557500.2557524", "10.1109/mcg.2015.91", "10.1109/vast.2012.6400494", "10.1109/tvcg.2013.220", "10.1109/mcg.2019.2945378", "10.1109/vast.2012.6400486", "10.1109/tvcg.2018.2865158", "10.1109/tvcg.2016.2598839", "10.1145/1142473.1142574", "10.1177/1555343416672782", "10.1109/vast.2011.6102449", "10.1111/cgf.12090", "10.1109/vast.2016.7883518", "10.1111/cgf.13678", "10.1109/mcg.2009.53", "10.1109/tvcg.2014.2346250", "10.1109/tvcg.2016.2598797", "10.1111/cgf.13400", "10.1109/tvcg.2014.2346573", "10.1080/01431160600746456", "10.1145/2642918.2647378", "10.1109/mcg.2019.2945720", "10.1145/2207676.2207741", "10.1145/3025171.3025189", "10.1145/634067.634292", "10.1109/tvcg.2015.2467611", "10.1109/tit.1982.1056489", "10.1109/tvcg.2018.2865117", "10.1109/vast.2009.5333023", "10.1145/3332165.3347866", "10.1109/mcg.2019.2933419", "10.1145/3184900", "10.1109/tvcg.2012.273", "10.1109/vast.2010.5652885", "10.1109/vast.2015.7347627", "10.1145/3290605.3300803", "10.1109/tvcg.2012.258", "10.1109/mcg.2009.87", "10.1109/tvcg.2019.2934556", "10.1145/1869397.1869399", "10.1109/mcg.2015.50", "10.1145/3172944.3172979", "10.1111/cgf.13208", "10.1111/cgf.12619", "10.1145/3290605.3300358", "10.1109/vast.2008.4677352", "10.1109/tvcg.2016.2598468", "10.1109/vast.2016.7883519", "10.1109/mcse.2008.79"], "wos": 1, "children": [], "len": 1}], "len": 3}, "index": 946, "embedding": [-0.02032618224620819, -0.032467834651470184, -1.060706377029419, -0.4188734292984009, 0.1950675994157791, 0.16650904715061188, -0.700136661529541, 0.9779250621795654, 0.9376266598701477, 0.4538009464740753, 0.1662236899137497, -0.2483995109796524, -0.1082504466176033, -1.1815917491912842, -0.678647518157959, -0.4294087290763855, 0.3685894310474396, 0.08175134658813477, -0.650787889957428, 0.15400171279907227, -0.06630208343267441, -0.37700799107551575, -1.0261266231536865, 0.21494922041893005, -1.2699415683746338, 0.09129026532173157, -0.5500518083572388, -0.16255053877830505, 0.6028516292572021, -1.434091567993164, -0.42042702436447144, -0.4444390833377838], "projection": [-1.7404905557632446, 8.61652946472168], "size": 2, "height": 2, "width": 1}